{
    "data-sheet": {
        "foundry": "SkyWater",
        "electrical-params": [
            {
                "conditions": [
                    {
                        "condition": "VOLTAGE:dvdd",
                        "unit": "V",
                        "display": "dvdd",
                        "typ": "1.8"
                    },
                    {
                        "condition": "VOLTAGE:vdd",
                        "unit": "V",
                        "display": "vdd",
                        "typ": "3.3"
                    },
                    {
			"display": "Digital",
                        "condition": "DIGITAL:b7:0",
                        "max": "11111111",
                        "typ": "10000000",
                        "min": "00000000"
                    },
                    {
                        "condition": "TEMPERATURE",
                        "unit": "\u00b0C",
                        "display": "Temp",
                        "typ": "27"
                    },
                    {
                        "condition": "SIGMA",
                        "display": "Sigma",
                        "typ": "3"
                    },
                    {
                        "condition": "CORNER",
                        "display": "Corner",
                        "typ": "tt"
                    }
                ],
                "typ": {
                    "penalty": "10",
                    "target": "170"
                },
                "min": {
                    "penalty": "0"
                },
                "unit": "\u00b5A",
                "method": "dccurrent_vdd",
                "display": "idd @ 3\u03c3",
                "max": {
                    "penalty": "fail",
                    "target": "250"
                }
            },
            {
                "conditions": [
                    {
                        "condition": "VOLTAGE:dvdd",
                        "unit": "V",
                        "display": "dvdd",
                        "typ": "1.8"
                    },
                    {
                        "condition": "VOLTAGE:vdd",
                        "unit": "V",
                        "display": "vdd",
                        "typ": "3.3"
                    },
                    {
			"display": "Digital",
                        "condition": "DIGITAL:b7:0",
                        "max": "11111111",
                        "min": "00000000"
                    },
                    {
			"display": "ena",
                        "condition": "DIGITAL:ena",
                        "typ": "0"
                    },
                    {
                        "condition": "TEMPERATURE",
                        "unit": "\u00b0C",
                        "display": "Temp",
                        "typ": "27"
                    },
                    {
                        "condition": "SIGMA",
                        "display": "Sigma",
                        "typ": "3"
                    },
                    {
                        "condition": "CORNER",
                        "display": "Corner",
                        "typ": "tt"
                    }
                ],
                "typ": {
                    "penalty": "10",
                    "target": "170"
                },
                "min": {
                    "penalty": "0"
                },
                "unit": "\u00b5A",
                "method": "dccurrent_vdd",
                "display": "Standby current",
                "max": {
                    "penalty": "fail",
                    "target": "250"
                }
            },
            {
                "conditions": [
                    {
                        "condition": "VOLTAGE:dvdd",
                        "unit": "V",
                        "display": "dvdd",
                        "typ": "1.8"
                    },
                    {
                        "condition": "VOLTAGE:vdd",
                        "unit": "V",
                        "display": "vdd",
                        "typ": "3.3"
                    },
                    {
			"display": "Digital",
                        "condition": "DIGITAL:b7:0",
                        "max": "11111111",
                        "typ": "11111100",
                        "min": "00000000"
                    },
                    {
                        "condition": "TEMPERATURE",
                        "unit": "\u00b0C",
                        "display": "Temp",
                        "typ": "27"
                    },
                    {
                        "condition": "SIGMA",
                        "display": "Sigma",
                        "typ": "3"
                    },
                    {
                        "condition": "CORNER",
                        "display": "Corner",
                        "typ": "tt"
                    }
                ],
		"evaluate": {
		    "tool": "octave",
		    "script": "inl.m"
		},
                "typ": {
                    "penalty": "0",
                    "target": "0"
                },
                "min": {
                    "penalty": "fail",
                    "target": "-2"
                },
                "unit": "lsb",
                "method": "voltage_output",
                "display": "INL",
                "max": {
                    "penalty": "fail",
                    "target": "2"
                }
            },
            {
                "conditions": [
                    {
                        "condition": "VOLTAGE:dvdd",
                        "unit": "V",
                        "display": "dvdd",
                        "typ": "1.8"
                    },
                    {
                        "condition": "VOLTAGE:vdd",
                        "unit": "V",
                        "display": "vdd",
                        "typ": "3.3"
                    },
                    {
			"display": "Digital",
                        "condition": "DIGITAL:b7:0",
                        "max": "11100000",
                        "min": "00011111"
                    },
                    {
                        "condition": "TEMPERATURE",
                        "unit": "\u00b0C",
                        "display": "Temp",
                        "typ": "27"
                    },
                    {
                        "condition": "SIGMA",
                        "display": "Sigma",
                        "typ": "3"
                    },
                    {
                        "condition": "ITERATIONS",
                        "display": "Iterations",
                        "min": "1",
                        "max": "10",
                        "linstep": "1"
                    },
                    {
                        "condition": "CORNER",
                        "display": "Corner",
                        "typ": "mc"
                    }
                ],
		"evaluate": {
		    "tool": "octave",
		    "script": "inl.m"
		},
                "typ": {
                    "penalty": "0",
                    "target": "0"
                },
                "min": {
                    "penalty": "fail",
                    "target": "-2"
                },
                "unit": "lsb",
                "method": "voltage_output",
                "display": "INL (Monte Carlo)",
                "max": {
                    "penalty": "fail",
                    "target": "2"
                }
            },
            {
                "conditions": [
                    {
                        "condition": "VOLTAGE:dvdd",
                        "unit": "V",
                        "display": "dvdd",
                        "typ": "1.8"
                    },
                    {
                        "condition": "VOLTAGE:vdd",
                        "unit": "V",
                        "display": "vdd",
                        "typ": "3.3"
                    },
                    {
			"display": "Digital",
                        "condition": "DIGITAL:b7:0",
			"enum": [
			    "00000000",
			    "00000001",
			    "00001111",
			    "00010000",
			    "00011111",
			    "00100000",
			    "01111111",
			    "10000000",
			    "01111111",
			    "10000000",
			    "10000001",
			    "11111110",
			    "11111111"
			]
                    },
                    {
                        "condition": "TEMPERATURE",
                        "unit": "\u00b0C",
                        "display": "Temp",
                        "typ": "27"
                    },
                    {
                        "condition": "SIGMA",
                        "display": "Sigma",
                        "typ": "3"
                    },
                    {
                        "condition": "CORNER",
                        "display": "Corner",
                        "typ": "tt"
                    }
                ],
		"evaluate": {
		    "tool": "octave",
		    "script": "dnl.m"
		},
                "typ": {
                    "penalty": "0",
                    "target": "0"
                },
                "min": {
                    "penalty": "fail",
                    "target": "-2"
                },
                "unit": "lsb",
                "method": "voltage_output",
                "display": "DNL",
                "max": {
                    "penalty": "fail",
                    "target": "2"
                }
            },
            {
                "conditions": [
                    {
                        "condition": "VOLTAGE:dvdd",
                        "unit": "V",
                        "display": "dvdd",
                        "typ": "1.8"
                    },
                    {
                        "condition": "VOLTAGE:vdd",
                        "unit": "V",
                        "display": "vdd",
                        "typ": "3.3"
                    },
                    {
                        "condition": "TEMPERATURE",
                        "unit": "\u00b0C",
                        "display": "Temp",
                        "max": "110",
                        "typ": "27",
                        "min": "-40"
                    },
                    {
                        "condition": "DIGITAL:b7:0",
			"display": "Digital",
                        "max": "11100110",
                        "min": "00011001"
                    },
                    {
                        "condition": "SIGMA",
                        "display": "Sigma",
                        "typ": "3"
                    },
                    {
                        "condition": "CORNER",
                        "display": "Corner",
                        "min": "ss",
                        "typ": "tt",
                        "max": "ff"
                    }
                ],
		"evaluate": {
		    "tool": "octave",
		    "script": "offset_err.m"
		},
                "typ": {
                    "penalty": "0",
                    "target": "0"
                },
                "min": {
                    "penalty": "fail",
                    "target": "-0.02"
                },
                "unit": "%FSR",
                "method": "voltage_output",
                "display": "Offset Error",
                "max": {
                    "penalty": "fail",
                    "target": "0.02"
                }
            },
            {
                "conditions": [
                    {
                        "condition": "VOLTAGE:dvdd",
                        "unit": "V",
                        "display": "dvdd",
                        "typ": "1.8"
                    },
                    {
                        "condition": "VOLTAGE:vdd",
                        "unit": "V",
                        "display": "VDD",
                        "typ": "3.3"
                    },
                    {
                        "condition": "TEMPERATURE",
                        "unit": "\u00b0C",
                        "display": "Temp",
                        "max": "110",
                        "typ": "27",
                        "min": "-40"
                    },
                    {
                        "condition": "DIGITAL:b7:0",
			"display": "Digital",
                        "max": "11100110",
                        "min": "00011001"
                    },
                    {
                        "condition": "SIGMA",
                        "display": "Sigma",
                        "typ": "3"
                    },
                    {
                        "condition": "CORNER",
                        "display": "Corner",
                        "min": "ss",
                        "typ": "tt",
                        "max": "ff"
                    }
                ],
		"evaluate": {
		    "tool": "octave",
		    "script": "gain_err.m"
		},
                "typ": {
                    "penalty": "0",
                    "target": "0"
                },
                "min": {
                    "penalty": "fail",
                    "target": "-0.02"
                },
                "unit": "%FSR",
                "method": "voltage_output",
                "display": "Gain Error",
                "max": {
                    "penalty": "fail",
                    "target": "0.02"
                }
            },
            {
                "conditions": [
                    {
                        "condition": "VOLTAGE:dvdd",
                        "unit": "V",
                        "display": "dvdd",
                        "typ": "1.8"
                    },
                    {
                        "condition": "VOLTAGE:vdd",
                        "unit": "V",
                        "display": "VDD",
                        "typ": "3.3"
                    },
		    {
			"condition": "FREQUENCY",
			"display": "Frequency",
			"typ": "1"
		    },
		    {
			"condition": "MAXTIME",
			"unit": "ns",
			"display": "Simulation time",
			"typ": "4000"
		    },
                    {
                        "condition": "TEMPERATURE",
                        "unit": "\u00b0C",
                        "display": "Temp",
                        "typ": "27"
                    },
                    {
                        "condition": "CORNER",
                        "display": "Corner",
                        "typ": "tt"
                    }
                ],
		"plot": {
		    "ylabel": "Output",
		    "filename": "transient_sine.png",
		    "xaxis": "TIME",
		    "xlabel": "Time"
		},
		"variables": [
		    {
			"unit": "ms",
			"display": "Time",
			"condition": "TIME"
		    },
		    {
			"unit": "V",
			"display": "out",
			"condition": "VOLTAGE:out"
		    },
		    {
			"result": true,
			"condition": "TRACE:out"
		    }
		],
                "unit": "V",
                "method": "transient_sine",
                "display": "Digital sine wave transient response"
            }
        ],
        "pins": [
            {
                "Vmin": "-0.3",
                "dir": "input",
                "type": "digital",
                "description": "Digital input (8 bits)",
                "Vmax": "2.2",
                "name": "b7:0"
            },
            {
                "Vmin": "-0.3",
                "dir": "input",
                "type": "digital",
                "description": "Enable input (active low)",
                "Vmax": "2.2",
                "name": "ena"
            },
            {
                "Vmin": "-0.3",
                "dir": "input",
                "type": "signal",
                "description": "reference high voltage",
                "Vmax": "2.2",
                "name": "Vhigh"
            },
            {
                "Vmin": "-0.3",
                "dir": "input",
                "type": "signal",
                "description": "reference low voltage",
                "Vmax": "2.2",
                "name": "Vlow"
            },
            {
                "Vmin": "-0.3",
                "dir": "output",
                "type": "signal",
                "description": "DAC voltage output",
                "Vmax": "2.2",
                "name": "out"
            },
            {
                "Vmin": "-0.3",
                "dir": "inout",
                "type": "power",
                "description": "positive digital power supply",
                "Vmax": "2.2",
                "name": "dvdd"
            },
            {
                "Vmin": "-0.3",
                "dir": "inout",
                "type": "ground",
                "description": "digital ground",
                "Vmax": "POWER + 0.3",
                "name": "dvss"
            },
            {
                "Vmin": "-0.3",
                "dir": "inout",
                "type": "power",
                "description": "positive analog power supply",
                "Vmax": "2.2",
                "name": "vdd"
            },
            {
                "Vmin": "-0.3",
                "dir": "inout",
                "type": "ground",
                "description": "analog ground",
                "Vmax": "POWER + 0.3",
                "name": "vss"
            }
        ],
        "global-conditions": [
            {
                "condition": "VOLTAGE:dvdd",
                "unit": "V",
                "display": "dvdd",
                "typ": "1.8"
            },
            {
                "condition": "VOLTAGE:dvss",
                "unit": "V",
                "display": "dvss",
                "typ": "0"
            },
            {
                "condition": "VOLTAGE:vdd",
                "unit": "V",
                "display": "vdd",
                "typ": "3.3"
            },
            {
                "condition": "VOLTAGE:vss",
                "unit": "V",
                "display": "vss",
                "typ": "0"
            },
            {
                "condition": "RESISTANCE:out",
                "unit": "MEG\u03a9",
                "display": "RLoad",
                "typ": "100"
            },
            {
                "condition": "CAPACITANCE:out",
                "display": "CLoad",
                "max": "100",
                "unit": "fF"
            },
            {
                "condition": "VOLTAGE:Vlow",
                "display": "Vlow",
                "typ": "0",
                "unit": "V"
            },
            {
                "condition": "VOLTAGE:Vhigh",
                "display": "Vhigh",
                "typ": "3.3",
                "unit": "V"
            },
            {
                "condition": "DIGITAL:ena",
                "display": "ena",
                "typ": "1"
            },
            {
                "condition": "DIGITAL:b7:0",
                "display": "D",
                "typ": "00000000"
            },
            {
                "typ": "27",
                "condition": "TEMPERATURE",
                "min": "-40",
                "unit": "\u00b0C",
                "display": "Temp",
                "max": "130"
            },
            {
                "condition": "SIGMA",
                "display": "Sigma",
                "typ": "3"
            },
            {
                "condition": "CORNER",
                "display": "Corner",
                "max": "ff",
                "min": "ss",
                "typ": "tt"
            }
        ],
        "category": "DAC",
        "node": "sky130A",
        "ip-name": "dac_3v_8bit"
    }
}
